rabboni_multi_python_sdk/__init__.py
rabboni_multi_python_sdk/BleakUWPBridge.dll
rabboni_multi_python_sdk/command.py
rabboni_multi_python_sdk/constants.py
rabboni_multi_python_sdk/errors.py
rabboni_multi_python_sdk/muls.pkl
rabboni_multi_python_sdk-0.1.0.dist-info/WHEEL
rabboni_multi_python_sdk-0.1.0.dist-info/METADATA
rabboni_multi_python_sdk-0.1.0.dist-info/RECORD
