Metadata-Version: 2.1
Name: rabboni-multi-python-sdk
Version: 0.1.0
Summary: 
License: MIT
Author: NCTUTWT Lab
Author-email: nctutwtlab@nctu.edu.tw
Requires-Python: >=3.7,<4.0
Classifier: License :: OSI Approved :: MIT License
Classifier: Programming Language :: Python :: 3
Classifier: Programming Language :: Python :: 3.7
Classifier: Programming Language :: Python :: 3.8
Classifier: Programming Language :: Python :: 3.9
Requires-Dist: bleak (>=0.10.0,<0.11.0)
